sample_package/__init__.py
sample_package/file1.py
sample_package/sub_package_1/__init__.py
sample_package/sub_package_1/sub_file1.py
sample_package_abdullah-0.1.5.dist-info/LICENSE
sample_package_abdullah-0.1.5.dist-info/METADATA
sample_package_abdullah-0.1.5.dist-info/WHEEL
sample_package_abdullah-0.1.5.dist-info/top_level.txt
sample_package_abdullah-0.1.5.dist-info/RECORD
